xrdfit/__init__.py
xrdfit/plotting.py
xrdfit/pv_fit.py
xrdfit/spectrum_fitting.py
xrdfit-1.3.0.dist-info/LICENSE
xrdfit-1.3.0.dist-info/METADATA
xrdfit-1.3.0.dist-info/WHEEL
xrdfit-1.3.0.dist-info/top_level.txt
xrdfit-1.3.0.dist-info/RECORD
