Metadata-Version: 2.1
Name: xrdfit
Version: 1.3.0
Summary: Automated fitting of XRD peaks using Pseudo-Voight fits
Home-page: https://github.com/LightForm-group/xrdfit
Author: Peter Crowther, Christopher Daniel
Classifier: Programming Language :: Python :: 3
Classifier: License :: OSI Approved :: GNU General Public License v3 (GPLv3)
Classifier: Operating System :: OS Independent
Requires-Python: >=3.7
License-File: LICENSE
Requires-Dist: numpy
Requires-Dist: matplotlib
Requires-Dist: pandas
Requires-Dist: dill
Requires-Dist: tqdm
Requires-Dist: lmfit
Requires-Dist: notebook
Requires-Dist: ipywidgets
Provides-Extra: documentation_compilation
Requires-Dist: sphinx ; extra == 'documentation_compilation'
